alteia_cli/plugins/dataflow_management/__init__.py
alteia_cli/plugins/dataflow_management/color_manager.py
alteia_cli/plugins/dataflow_management/datastreams.py
alteia_cli/plugins/dataflow_management/datastreamtemplates.py
alteia_cli_dataflow_management-1.1.0.dist-info/WHEEL
alteia_cli_dataflow_management-1.1.0.dist-info/METADATA
alteia_cli_dataflow_management-1.1.0.dist-info/RECORD
