Metadata-Version: 2.1
Name: alteia-cli-dataflow-management
Version: 1.1.0
Summary: Alteia CLI extension for dataflow management
License: MIT
Keywords: cli,alteia
Author: Alteia Backend Team
Author-email: backend-team@alteia.com
Requires-Python: >=3.7.0,<4.0.0
Classifier: License :: OSI Approved :: MIT License
Classifier: Programming Language :: Python :: 3
Classifier: Programming Language :: Python :: 3.10
Classifier: Programming Language :: Python :: 3.7
Classifier: Programming Language :: Python :: 3.8
Classifier: Programming Language :: Python :: 3.9
Requires-Dist: alteia (>=2.9.0)
Requires-Dist: alteia-cli (==1.6.0)
Requires-Dist: pydantic (>=1.10.2,<2.0.0)
Requires-Dist: python-dateutil (>=2.8.2,<3.0.0)
Requires-Dist: tabulate (>=0.8.7,<0.9.0)
Requires-Dist: types-cachetools (>=5.2.1,<6.0.0)
Requires-Dist: types-python-dateutil (>=2.8.19.2,<3.0.0.0)
Requires-Dist: types-pyyaml (>=6.0.12,<7.0.0)
